{"nameEn": "The Racers", "nameTr": "al-'Adiyat", "nameAr": "الـعاديات", "noVerses": 11, "verses": [["وَالْعَادِيَاتِ ضَبْحًا", "Wa maiy-y'amal mithqala zarratin sharraiy-yarah"], ["فَالْمُورِيَاتِ قَدْحًا", "Wal'aadi yaati dabha"], ["فَالْمُغِيرَاتِ صُبْحًا", "Fal moori yaati qadha"], ["فَأَثَرْنَ بِهِ نَقْعًا", "Fal mugheeraati subha"], ["فَوَسَطْنَ بِهِ جَمْعًا", "Fa atharna bihee naq'a"], ["إِنَّ الْإِنْسَانَ لِرَبِّهِ لَكَنُودٌ", "Fawa satna bihee jam'a"], ["وَإِنَّهُ عَلَىٰ ذَٰلِكَ لَشَهِيدٌ", "Innal-insana lirabbihee lakanood"], ["وَإِنَّهُ لِحُبِّ الْخَيْرِ لَشَدِيدٌ", "Wa innahu 'alaa zaalika la shaheed"], ["أَفَلَا يَعْلَمُ إِذَا بُعْثِرَ مَا فِي الْقُبُورِ", "Wa innahu lihubbil khairi la shadeed"], ["وَحُصِّلَ مَا فِي الصُّدُورِ", "Afala ya'lamu iza b'uthira ma filquboor"], ["إِنَّ رَبَّهُمْ بِهِمْ يَوْمَئِذٍ لَخَبِيرٌ", "Wa hussila maa fis sudoor"]]}